{"config": {"background": "transparent", "title": {"color": "#DBDEE1", "fontSize": 16}, "axis": {"domainColor": "#666666", "gridColor": "#666666", "tickColor": "#DBDEE1", "titleColor": "#DBDEE1", "labelColor": "#DBDEE1"}, "legend": {"labelColor": "#DBDEE1", "titleColor": "#DBDEE1"}, "axisX": {"domain": false, "grid": true, "labels": false, "ticks": false}, "axisY": {"domain": true, "grid": false, "labels": false, "ticks": false}, "view": {"strokeWidth": 0.5}}, "data": {"name": "data-3840827af4f77d740f1164fdc5e2305b"}, "mark": {"type": "bar", "tooltip": true}, "encoding": {"color": {"field": "closest_cm_hex_color", "scale": null, "type": "nominal"}, "tooltip": [{"field": "original_color_name", "title": "Nome del colore pi\u00f9 vicino", "type": "nominal"}, {"field": "closest_cm_hex_color", "title": "Codice esadecimale del colore pi\u00f9 vicino", "type": "nominal"}, {"field": "cw_tf_idf_norm", "title": "Peso tf-idf normalizzato", "type": "quantitative"}], "x": {"field": "cw_tf_idf_norm", "title": null, "type": "quantitative"}, "y": {"field": "original_color_name", "sort": "-x", "title": null, "type": "nominal"}}, "height": "container", "transform": [{"window": [{"op": "rank", "field": "cw_tf_idf_norm", "as": "rank"}], "sort": [{"field": "cw_tf_idf_norm", "order": "descending"}]}, {"filter": "(datum.rank <= 5)"}], "width": "container", "$schema": "https://vega.github.io/schema/vega-lite/v5.17.0.json", "datasets": {"data-3840827af4f77d740f1164fdc5e2305b": [{"original_color_name": "Alloy Orange", "closest_cm_hex_color": "#C35214", "cw_tf_idf": 0.015330040923166177, "cw_tf_idf_norm": 0.07998047862341856}, {"original_color_name": "Amber", "closest_cm_hex_color": "#893101", "cw_tf_idf": 0.0027846101707309744, "cw_tf_idf_norm": 0.011307385020420469}, {"original_color_name": "Apple", "closest_cm_hex_color": "#A91B0D", "cw_tf_idf": 0.01873303608176238, "cw_tf_idf_norm": 0.09860831290574991}, {"original_color_name": "Beaver", "closest_cm_hex_color": "#9F8170", "cw_tf_idf": 0.002734836508650347, "cw_tf_idf_norm": 0.011034926352202686}, {"original_color_name": "Brick", "closest_cm_hex_color": "#7E2811", "cw_tf_idf": 0.04276193159229264, "cw_tf_idf_norm": 0.2301413485690328}, {"original_color_name": "Bronze", "closest_cm_hex_color": "#B2560D", "cw_tf_idf": 0.006796435191345486, "cw_tf_idf_norm": 0.033267925124317}, {"original_color_name": "Cafe Au Lait", "closest_cm_hex_color": "#A67B5B", "cw_tf_idf": 0.0013120528319555166, "cw_tf_idf_norm": 0.0032466759099039322}, {"original_color_name": "Cedar Brown", "closest_cm_hex_color": "#4A3728", "cw_tf_idf": 0.0012594196198784495, "cw_tf_idf_norm": 0.0029585642004759183}, {"original_color_name": "Cinnamon Brown", "closest_cm_hex_color": "#652A0E", "cw_tf_idf": 0.08686444065511104, "cw_tf_idf_norm": 0.4715563938364186}, {"original_color_name": "Copper", "closest_cm_hex_color": "#B87333", "cw_tf_idf": 0.029219314989219577, "cw_tf_idf_norm": 0.15600970686100876}, {"original_color_name": "Currant", "closest_cm_hex_color": "#680C07", "cw_tf_idf": 0.012742380982184042, "cw_tf_idf_norm": 0.06581575069605737}, {"original_color_name": "Dark Chocolate", "closest_cm_hex_color": "#2E1503", "cw_tf_idf": 0.002225269045339205, "cw_tf_idf_norm": 0.00824557819863564}, {"original_color_name": "Deep Black", "closest_cm_hex_color": "#050203", "cw_tf_idf": 0.0007189392023472951, "cw_tf_idf_norm": 0.0}, {"original_color_name": "Deer", "closest_cm_hex_color": "#BA8759", "cw_tf_idf": 0.011411147414217237, "cw_tf_idf_norm": 0.058528641211778254}, {"original_color_name": "Ebony", "closest_cm_hex_color": "#080402", "cw_tf_idf": 0.010568305553214722, "cw_tf_idf_norm": 0.053914964794018305}, {"original_color_name": "Grape", "closest_cm_hex_color": "#663046", "cw_tf_idf": 0.03758334492130085, "cw_tf_idf_norm": 0.2017940104659369}, {"original_color_name": "Jam", "closest_cm_hex_color": "#60100B", "cw_tf_idf": 0.1834022885933161, "cw_tf_idf_norm": 1.0}, {"original_color_name": "Khaki", "closest_cm_hex_color": "#C3B091", "cw_tf_idf": 0.0012587344457019331, "cw_tf_idf_norm": 0.0029548135894935787}, {"original_color_name": "Mahogany", "closest_cm_hex_color": "#420C09", "cw_tf_idf": 0.08633548904677811, "cw_tf_idf_norm": 0.4686609377913201}, {"original_color_name": "Oil", "closest_cm_hex_color": "#050100", "cw_tf_idf": 0.0011065287824222516, "cw_tf_idf_norm": 0.002121646999395981}, {"original_color_name": "Rust", "closest_cm_hex_color": "#8D4004", "cw_tf_idf": 0.062447558140534425, "cw_tf_idf_norm": 0.3378995356937482}, {"original_color_name": "Sienna", "closest_cm_hex_color": "#A0522D", "cw_tf_idf": 0.016494053446856397, "cw_tf_idf_norm": 0.08635222803337199}, {"original_color_name": "Soot", "closest_cm_hex_color": "#160D08", "cw_tf_idf": 0.009933684905955874, "cw_tf_idf_norm": 0.050441081435876736}, {"original_color_name": "Vampire Black", "closest_cm_hex_color": "#0F0404", "cw_tf_idf": 0.0011796024690909652, "cw_tf_idf_norm": 0.002521648898377619}]}}