{"config": {"background": "transparent", "title": {"color": "#DBDEE1", "fontSize": 16}, "axis": {"domainColor": "#666666", "gridColor": "#666666", "tickColor": "#DBDEE1", "titleColor": "#DBDEE1", "labelColor": "#DBDEE1"}, "legend": {"labelColor": "#DBDEE1", "titleColor": "#DBDEE1"}, "axisX": {"domain": false, "grid": true, "labels": false, "ticks": false}, "axisY": {"domain": true, "grid": false, "labels": false, "ticks": false}, "view": {"strokeWidth": 0.5}}, "data": {"name": "data-6419d67ac2dc65dbcac0310e583619e0"}, "mark": {"type": "bar", "tooltip": true}, "encoding": {"color": {"field": "closest_cm_hex_color", "scale": null, "type": "nominal"}, "tooltip": [{"field": "original_color_name", "title": "Nome del colore pi\u00f9 vicino", "type": "nominal"}, {"field": "closest_cm_hex_color", "title": "Codice esadecimale del colore pi\u00f9 vicino", "type": "nominal"}, {"field": "cw_tf_idf_norm", "title": "Peso tf-idf normalizzato", "type": "quantitative"}], "x": {"field": "cw_tf_idf_norm", "title": null, "type": "quantitative"}, "y": {"field": "original_color_name", "sort": "-x", "title": null, "type": "nominal"}}, "height": "container", "transform": [{"window": [{"op": "rank", "field": "cw_tf_idf_norm", "as": "rank"}], "sort": [{"field": "cw_tf_idf_norm", "order": "descending"}]}, {"filter": "(datum.rank <= 5)"}], "width": "container", "$schema": "https://vega.github.io/schema/vega-lite/v5.17.0.json", "datasets": {"data-6419d67ac2dc65dbcac0310e583619e0": [{"original_color_name": "Ash", "closest_cm_hex_color": "#564C4D", "cw_tf_idf": 0.0005497319565572827, "cw_tf_idf_norm": 0.009483453987076906}, {"original_color_name": "Astros Navy", "closest_cm_hex_color": "#002D62", "cw_tf_idf": 0.006198887403356463, "cw_tf_idf_norm": 0.16693423171726962}, {"original_color_name": "Beaver", "closest_cm_hex_color": "#9F8170", "cw_tf_idf": 0.03608834295435236, "cw_tf_idf_norm": 1.0}, {"original_color_name": "Black Magic", "closest_cm_hex_color": "#0B0510", "cw_tf_idf": 0.0010537493829466977, "cw_tf_idf_norm": 0.023531206172679776}, {"original_color_name": "Black Rock", "closest_cm_hex_color": "#010127", "cw_tf_idf": 0.0003231629854326906, "cw_tf_idf_norm": 0.003168623204130536}, {"original_color_name": "Blood", "closest_cm_hex_color": "#710C04", "cw_tf_idf": 0.02519779251406296, "cw_tf_idf_norm": 0.6964633646778077}, {"original_color_name": "Blue Sapphire", "closest_cm_hex_color": "#126180", "cw_tf_idf": 0.0048899693464470725, "cw_tf_idf_norm": 0.1304526429229221}, {"original_color_name": "Braves Navy", "closest_cm_hex_color": "#13274F", "cw_tf_idf": 0.006667768286883769, "cw_tf_idf_norm": 0.1800026736232228}, {"original_color_name": "Brunette", "closest_cm_hex_color": "#3B1E08", "cw_tf_idf": 0.00020947637625542907, "cw_tf_idf_norm": 0.0}, {"original_color_name": "Camouflage Green", "closest_cm_hex_color": "#78866B", "cw_tf_idf": 0.0005089711911116342, "cw_tf_idf_norm": 0.008347387847503482}, {"original_color_name": "Carob", "closest_cm_hex_color": "#362511", "cw_tf_idf": 0.0002730191930704659, "cw_tf_idf_norm": 0.0017710374623101386}, {"original_color_name": "Chamoisee", "closest_cm_hex_color": "#A0785A", "cw_tf_idf": 0.0015010454010304223, "cw_tf_idf_norm": 0.035998044195840365}, {"original_color_name": "Clay", "closest_cm_hex_color": "#80400B", "cw_tf_idf": 0.0012832220764540485, "cw_tf_idf_norm": 0.02992696822965171}, {"original_color_name": "Coconut", "closest_cm_hex_color": "#965A3E", "cw_tf_idf": 0.00813851773304009, "cw_tf_idf_norm": 0.22099475577149705}, {"original_color_name": "Coffee", "closest_cm_hex_color": "#6F4E37", "cw_tf_idf": 0.011194099458600903, "cw_tf_idf_norm": 0.30615858665533446}, {"original_color_name": "Crow", "closest_cm_hex_color": "#0D0907", "cw_tf_idf": 0.0021759533748374367, "cw_tf_idf_norm": 0.05480878261027587}, {"original_color_name": "Currant", "closest_cm_hex_color": "#680C07", "cw_tf_idf": 0.002134955360973138, "cw_tf_idf_norm": 0.05366610398705184}, {"original_color_name": "Dark Brown", "closest_cm_hex_color": "#654321", "cw_tf_idf": 0.0034972888962714497, "cw_tf_idf_norm": 0.09163646551820397}, {"original_color_name": "Dark Silver", "closest_cm_hex_color": "#746D69", "cw_tf_idf": 0.00030232331696231486, "cw_tf_idf_norm": 0.002587789123850593}, {"original_color_name": "Davy\u2019s Gray", "closest_cm_hex_color": "#555555", "cw_tf_idf": 0.00029465833866524754, "cw_tf_idf_norm": 0.002374154217620122}, {"original_color_name": "Denim", "closest_cm_hex_color": "#151E3D", "cw_tf_idf": 0.017919109883765563, "cw_tf_idf_norm": 0.49359512148918827}, {"original_color_name": "Dirt", "closest_cm_hex_color": "#9B7653", "cw_tf_idf": 0.0007944287344056372, "cw_tf_idf_norm": 0.016303535031602853}, {"original_color_name": "Ebony", "closest_cm_hex_color": "#080402", "cw_tf_idf": 0.0015823796888321973, "cw_tf_idf_norm": 0.03826495771789202}, {"original_color_name": "Gray Cloud", "closest_cm_hex_color": "#B6B6B4", "cw_tf_idf": 0.001904122014540814, "cw_tf_idf_norm": 0.04723241840978108}, {"original_color_name": "Gray Wolf", "closest_cm_hex_color": "#504A4B", "cw_tf_idf": 0.0004493158709942047, "cw_tf_idf_norm": 0.00668470098453977}, {"original_color_name": "Imperial Blue", "closest_cm_hex_color": "#005A92", "cw_tf_idf": 0.018413188236911952, "cw_tf_idf_norm": 0.5073658561937235}, {"original_color_name": "Ink", "closest_cm_hex_color": "#070504", "cw_tf_idf": 0.0007713704383415634, "cw_tf_idf_norm": 0.01566086433814928}, {"original_color_name": "Khaki", "closest_cm_hex_color": "#C3B091", "cw_tf_idf": 0.0007941300208796228, "cw_tf_idf_norm": 0.016295209419494562}, {"original_color_name": "Mahogany", "closest_cm_hex_color": "#420C09", "cw_tf_idf": 0.019773427950478838, "cw_tf_idf_norm": 0.5452778596458413}, {"original_color_name": "Marengo", "closest_cm_hex_color": "#4C5866", "cw_tf_idf": 0.0010820631259286174, "cw_tf_idf_norm": 0.024320354372784972}, {"original_color_name": "Medium Gray", "closest_cm_hex_color": "#BEBEBE", "cw_tf_idf": 0.0047566831055475935, "cw_tf_idf_norm": 0.12673774739774277}, {"original_color_name": "Peanut Brown", "closest_cm_hex_color": "#795C34", "cw_tf_idf": 0.028171267118964796, "cw_tf_idf_norm": 0.7793387419818684}, {"original_color_name": "Pecan", "closest_cm_hex_color": "#4A2511", "cw_tf_idf": 0.0024074462660486347, "cw_tf_idf_norm": 0.06126085072974423}, {"original_color_name": "Perfect Gray", "closest_cm_hex_color": "#A1A1A1", "cw_tf_idf": 0.0070426910231751625, "cw_tf_idf_norm": 0.19045235534533925}, {"original_color_name": "Power Black", "closest_cm_hex_color": "#0E0C01", "cw_tf_idf": 0.0011500634169792675, "cw_tf_idf_norm": 0.026215628597867725}, {"original_color_name": "Raven", "closest_cm_hex_color": "#050301", "cw_tf_idf": 0.00343802937279374, "cw_tf_idf_norm": 0.08998481012522436}, {"original_color_name": "Roasted Coffee", "closest_cm_hex_color": "#4B371C", "cw_tf_idf": 0.0032419029069484955, "cw_tf_idf_norm": 0.08451845946951624}, {"original_color_name": "Sable", "closest_cm_hex_color": "#060606", "cw_tf_idf": 0.00048459188171562053, "cw_tf_idf_norm": 0.007667898451065952}, {"original_color_name": "Scarlet", "closest_cm_hex_color": "#900D09", "cw_tf_idf": 0.024605157298996178, "cw_tf_idf_norm": 0.6799456964349494}, {"original_color_name": "Slate", "closest_cm_hex_color": "#757C88", "cw_tf_idf": 0.02965472817123984, "cw_tf_idf_norm": 0.8206851164289546}, {"original_color_name": "Soot", "closest_cm_hex_color": "#160D08", "cw_tf_idf": 0.00041777428500528417, "cw_tf_idf_norm": 0.005805587762825687}, {"original_color_name": "Spanish Gray", "closest_cm_hex_color": "#989898", "cw_tf_idf": 0.002793473148104142, "cw_tf_idf_norm": 0.07202002232217035}, {"original_color_name": "Stone Gray", "closest_cm_hex_color": "#928E85", "cw_tf_idf": 0.007298015508092651, "cw_tf_idf_norm": 0.1975686471702699}, {"original_color_name": "Tawny", "closest_cm_hex_color": "#80471C", "cw_tf_idf": 0.011808445673580787, "cw_tf_idf_norm": 0.323281374345482}, {"original_color_name": "Tech Black", "closest_cm_hex_color": "#0D0E0E", "cw_tf_idf": 0.0007294305928450768, "cw_tf_idf_norm": 0.014491935397621105}, {"original_color_name": "Umber", "closest_cm_hex_color": "#352315", "cw_tf_idf": 0.0004927632091228353, "cw_tf_idf_norm": 0.007895646097146923}, {"original_color_name": "Vampire Black", "closest_cm_hex_color": "#0F0404", "cw_tf_idf": 0.00592471818887526, "cw_tf_idf_norm": 0.15929270787246189}, {"original_color_name": "Vintage Gray", "closest_cm_hex_color": "#989692", "cw_tf_idf": 0.00785226596226962, "cw_tf_idf_norm": 0.21301647222824774}, {"original_color_name": "Walnut", "closest_cm_hex_color": "#432616", "cw_tf_idf": 0.0007928371011862313, "cw_tf_idf_norm": 0.01625917373005668}, {"original_color_name": "Wood", "closest_cm_hex_color": "#3F301D", "cw_tf_idf": 0.002020688813090575, "cw_tf_idf_norm": 0.050481316986218334}, {"original_color_name": "X11 Gray", "closest_cm_hex_color": "#BBBCB6", "cw_tf_idf": 0.008135031957623733, "cw_tf_idf_norm": 0.2208976017711395}, {"original_color_name": "Yale Blue", "closest_cm_hex_color": "#00356B", "cw_tf_idf": 0.01757651993644982, "cw_tf_idf_norm": 0.48404660505068725}]}}