{"config": {"background": "transparent", "title": {"color": "#DBDEE1", "fontSize": 16}, "axis": {"domainColor": "#666666", "gridColor": "#666666", "tickColor": "#DBDEE1", "titleColor": "#DBDEE1", "labelColor": "#DBDEE1"}, "legend": {"labelColor": "#DBDEE1", "titleColor": "#DBDEE1"}, "axisX": {"domain": false, "grid": true, "labels": false, "ticks": false}, "axisY": {"domain": true, "grid": false, "labels": false, "ticks": false}, "view": {"strokeWidth": 0.5}}, "data": {"name": "data-0d9d93d50e6be36153cf69aa2ce8d9e9"}, "mark": {"type": "bar", "tooltip": true}, "encoding": {"color": {"field": "closest_cm_hex_color", "scale": null, "type": "nominal"}, "tooltip": [{"field": "original_color_name", "title": "Nome del colore pi\u00f9 vicino", "type": "nominal"}, {"field": "closest_cm_hex_color", "title": "Codice esadecimale del colore pi\u00f9 vicino", "type": "nominal"}, {"field": "cw_tf_idf_norm", "title": "Peso tf-idf normalizzato", "type": "quantitative"}], "x": {"field": "cw_tf_idf_norm", "title": null, "type": "quantitative"}, "y": {"field": "original_color_name", "sort": "-x", "title": null, "type": "nominal"}}, "height": "container", "transform": [{"window": [{"op": "rank", "field": "cw_tf_idf_norm", "as": "rank"}], "sort": [{"field": "cw_tf_idf_norm", "order": "descending"}]}, {"filter": "(datum.rank <= 5)"}], "width": "container", "$schema": "https://vega.github.io/schema/vega-lite/v5.17.0.json", "datasets": {"data-0d9d93d50e6be36153cf69aa2ce8d9e9": [{"original_color_name": "Anchor", "closest_cm_hex_color": "#41424C", "cw_tf_idf": 0.0030577839495333887, "cw_tf_idf_norm": 0.06115982853653658}, {"original_color_name": "Army Green", "closest_cm_hex_color": "#4B5320", "cw_tf_idf": 0.002184680960548802, "cw_tf_idf_norm": 0.04079547643494995}, {"original_color_name": "Ash", "closest_cm_hex_color": "#564C4D", "cw_tf_idf": 0.0014211249433646943, "cw_tf_idf_norm": 0.022986210197863687}, {"original_color_name": "Battleship Gray", "closest_cm_hex_color": "#848482", "cw_tf_idf": 0.0032193246704423826, "cw_tf_idf_norm": 0.06492762244039293}, {"original_color_name": "Bole", "closest_cm_hex_color": "#79443B", "cw_tf_idf": 0.0024604288654276538, "cw_tf_idf_norm": 0.04722705151495107}, {"original_color_name": "Cedar Brown", "closest_cm_hex_color": "#4A3728", "cw_tf_idf": 0.000435612184153507, "cw_tf_idf_norm": 0.0}, {"original_color_name": "Charcoal", "closest_cm_hex_color": "#28231D", "cw_tf_idf": 0.0009889925188612907, "cw_tf_idf_norm": 0.012907105031434161}, {"original_color_name": "Dark Brown", "closest_cm_hex_color": "#654321", "cw_tf_idf": 0.04330969846144595, "cw_tf_idf_norm": 1.0}, {"original_color_name": "Dark Silver", "closest_cm_hex_color": "#746D69", "cw_tf_idf": 0.008713522969152567, "cw_tf_idf_norm": 0.19307492016181624}, {"original_color_name": "Dijon", "closest_cm_hex_color": "#C49102", "cw_tf_idf": 0.007122036131683291, "cw_tf_idf_norm": 0.15595490255546599}, {"original_color_name": "Dim Gray", "closest_cm_hex_color": "#696969", "cw_tf_idf": 0.0012910784075513256, "cw_tf_idf_norm": 0.019952990201703776}, {"original_color_name": "Dirt", "closest_cm_hex_color": "#9B7653", "cw_tf_idf": 0.002405879952809865, "cw_tf_idf_norm": 0.04595474655514415}, {"original_color_name": "Dove", "closest_cm_hex_color": "#7C6E7F", "cw_tf_idf": 0.0005308442536209741, "cw_tf_idf_norm": 0.002221203475953847}, {"original_color_name": "Dull Black", "closest_cm_hex_color": "#161616", "cw_tf_idf": 0.00971284741610227, "cw_tf_idf_norm": 0.21638327571454974}, {"original_color_name": "Flint", "closest_cm_hex_color": "#7F7D9C", "cw_tf_idf": 0.0012877702698164508, "cw_tf_idf_norm": 0.019875830825910226}, {"original_color_name": "Fossil", "closest_cm_hex_color": "#787276", "cw_tf_idf": 0.0011527920775485515, "cw_tf_idf_norm": 0.01672758432113542}, {"original_color_name": "Graphite", "closest_cm_hex_color": "#594D5B", "cw_tf_idf": 0.002069078886180079, "cw_tf_idf_norm": 0.03809916067859646}, {"original_color_name": "Gray", "closest_cm_hex_color": "#808080", "cw_tf_idf": 0.0022897021912123903, "cw_tf_idf_norm": 0.04324500340525908}, {"original_color_name": "Gray Cloud", "closest_cm_hex_color": "#B6B6B4", "cw_tf_idf": 0.0006681904055852451, "cw_tf_idf_norm": 0.005424680538437955}, {"original_color_name": "Gunmetal", "closest_cm_hex_color": "#2A3439", "cw_tf_idf": 0.018262673972554083, "cw_tf_idf_norm": 0.41580038984626444}, {"original_color_name": "Indigo", "closest_cm_hex_color": "#281E5D", "cw_tf_idf": 0.01827463104708971, "cw_tf_idf_norm": 0.4160792779946507}, {"original_color_name": "Misty Gray", "closest_cm_hex_color": "#BCC2C2", "cw_tf_idf": 0.0013172688916241188, "cw_tf_idf_norm": 0.02056385999152049}, {"original_color_name": "Night Shadow", "closest_cm_hex_color": "#1C1C1C", "cw_tf_idf": 0.00155199729457008, "cw_tf_idf_norm": 0.026038691604906527}, {"original_color_name": "Peanut Brown", "closest_cm_hex_color": "#795C34", "cw_tf_idf": 0.014192867671524088, "cw_tf_idf_norm": 0.3208757709352487}, {"original_color_name": "Raisin Black", "closest_cm_hex_color": "#242124", "cw_tf_idf": 0.0005414797296898503, "cw_tf_idf_norm": 0.0024692665133814015}, {"original_color_name": "Rust", "closest_cm_hex_color": "#8D4004", "cw_tf_idf": 0.0016570004467629524, "cw_tf_idf_norm": 0.02848779691093577}, {"original_color_name": "Sienna", "closest_cm_hex_color": "#A0522D", "cw_tf_idf": 0.016264971274100176, "cw_tf_idf_norm": 0.3692057479095579}, {"original_color_name": "Silver Chalice", "closest_cm_hex_color": "#ACACAC", "cw_tf_idf": 0.011371458869293555, "cw_tf_idf_norm": 0.2550689153912544}, {"original_color_name": "Spanish Gray", "closest_cm_hex_color": "#989898", "cw_tf_idf": 0.0031764202986987013, "cw_tf_idf_norm": 0.06392691605877601}, {"original_color_name": "Stone Gray", "closest_cm_hex_color": "#928E85", "cw_tf_idf": 0.0009381018940776403, "cw_tf_idf_norm": 0.01172012638763263}, {"original_color_name": "Taupe", "closest_cm_hex_color": "#483C32", "cw_tf_idf": 0.006146370118440571, "cw_tf_idf_norm": 0.13319835896565038}, {"original_color_name": "Tortilla", "closest_cm_hex_color": "#9A7B4F", "cw_tf_idf": 0.007495458887606267, "cw_tf_idf_norm": 0.1646646568230631}, {"original_color_name": "Umber", "closest_cm_hex_color": "#352315", "cw_tf_idf": 0.001568834168248352, "cw_tf_idf_norm": 0.026431396736145425}, {"original_color_name": "Vintage Gray", "closest_cm_hex_color": "#989692", "cw_tf_idf": 0.0025259467407604493, "cw_tf_idf_norm": 0.04875519779214639}, {"original_color_name": "Vivid Tangelo", "closest_cm_hex_color": "#EC7625", "cw_tf_idf": 0.011683955812310355, "cw_tf_idf_norm": 0.2623576291610522}, {"original_color_name": "Wood Brown", "closest_cm_hex_color": "#C19A6B", "cw_tf_idf": 0.0016127772568539245, "cw_tf_idf_norm": 0.02745633026642211}]}}