{"config": {"background": "transparent", "title": {"color": "#DBDEE1", "fontSize": 16}, "axis": {"domainColor": "#313338", "gridColor": "#666666", "tickColor": "#DBDEE1", "titleColor": "#DBDEE1", "labelColor": "#DBDEE1", "grid": false}, "legend": {"labelColor": "#DBDEE1", "titleColor": "#DBDEE1"}, "view": {"stroke": null}}, "data": {"name": "data-a78b1476ca64e42b6a6bd9aaaf607a0f"}, "mark": {"type": "rect", "opacity": 1, "tooltip": true}, "encoding": {"color": {"field": "hex_color", "scale": null, "type": "nominal"}, "tooltip": [{"field": "scene", "type": "quantitative"}, {"field": "hex_color", "type": "nominal"}, {"field": "closest_cm_color_name", "type": "nominal"}, {"field": "frequency", "type": "quantitative"}], "x": {"axis": null, "field": "start_frame", "scale": {"domainMax": 752.0, "domainMin": 12.0, "padding": 0}, "title": null, "type": "quantitative"}, "x2": {"field": "end_frame"}, "y": {"axis": null, "field": "start_freq", "scale": {"padding": 0}, "title": null, "type": "quantitative"}, "y2": {"field": "end_freq"}}, "height": "container", "transform": [{"groupby": ["scene"], "stack": "frequency", "as": ["start_freq", "end_freq"]}], "width": "container", "$schema": "https://vega.github.io/schema/vega-lite/v5.17.0.json", "datasets": {"data-a78b1476ca64e42b6a6bd9aaaf607a0f": [{"scene": 1, "hex_color": "#1c1119", "closest_cm_color_name": "dull_black", "frequency": 0.36590576171875, "start_frame": 12, "end_frame": 43}, {"scene": 1, "hex_color": "#633735", "closest_cm_color_name": "grape", "frequency": 0.201080322265625, "start_frame": 12, "end_frame": 43}, {"scene": 1, "hex_color": "#be958f", "closest_cm_color_name": "khaki", "frequency": 0.1666412353515625, "start_frame": 12, "end_frame": 43}, {"scene": 1, "hex_color": "#456398", "closest_cm_color_name": "blue_yonder", "frequency": 0.141876220703125, "start_frame": 12, "end_frame": 43}, {"scene": 1, "hex_color": "#ccd8f2", "closest_cm_color_name": "beau_blue", "frequency": 0.1244964599609375, "start_frame": 12, "end_frame": 43}, {"scene": 2, "hex_color": "#231119", "closest_cm_color_name": "raisin", "frequency": 0.3429718017578125, "start_frame": 43, "end_frame": 67}, {"scene": 2, "hex_color": "#985a58", "closest_cm_color_name": "coconut", "frequency": 0.247161865234375, "start_frame": 43, "end_frame": 67}, {"scene": 2, "hex_color": "#633831", "closest_cm_color_name": "dark_brown", "frequency": 0.234100341796875, "start_frame": 43, "end_frame": 67}, {"scene": 2, "hex_color": "#95243d", "closest_cm_color_name": "alabama_crimson", "frequency": 0.12432861328125, "start_frame": 43, "end_frame": 67}, {"scene": 2, "hex_color": "#c79ca7", "closest_cm_color_name": "khaki", "frequency": 0.0514373779296875, "start_frame": 43, "end_frame": 67}, {"scene": 3, "hex_color": "#1a0d15", "closest_cm_color_name": "dark_raisin", "frequency": 0.455474853515625, "start_frame": 67, "end_frame": 90}, {"scene": 3, "hex_color": "#483644", "closest_cm_color_name": "anchor", "frequency": 0.269805908203125, "start_frame": 67, "end_frame": 90}, {"scene": 3, "hex_color": "#cd422d", "closest_cm_color_name": "prismatic_red", "frequency": 0.118438720703125, "start_frame": 67, "end_frame": 90}, {"scene": 3, "hex_color": "#c2abc6", "closest_cm_color_name": "medium_gray", "frequency": 0.1032257080078125, "start_frame": 67, "end_frame": 90}, {"scene": 3, "hex_color": "#7e130a", "closest_cm_color_name": "berry", "frequency": 0.0530548095703125, "start_frame": 67, "end_frame": 90}, {"scene": 4, "hex_color": "#291b22", "closest_cm_color_name": "charcoal_gray", "frequency": 0.2348175048828125, "start_frame": 90, "end_frame": 122}, {"scene": 4, "hex_color": "#695965", "closest_cm_color_name": "fog", "frequency": 0.216583251953125, "start_frame": 90, "end_frame": 122}, {"scene": 4, "hex_color": "#604134", "closest_cm_color_name": "dark_brown", "frequency": 0.213653564453125, "start_frame": 90, "end_frame": 122}, {"scene": 4, "hex_color": "#8c7786", "closest_cm_color_name": "rocket_metallic", "frequency": 0.2038421630859375, "start_frame": 90, "end_frame": 122}, {"scene": 4, "hex_color": "#c2a9b2", "closest_cm_color_name": "gray_cloud", "frequency": 0.131103515625, "start_frame": 90, "end_frame": 122}, {"scene": 5, "hex_color": "#ad7367", "closest_cm_color_name": "cafe_au_lait", "frequency": 0.298248291015625, "start_frame": 122, "end_frame": 168}, {"scene": 5, "hex_color": "#724d52", "closest_cm_color_name": "deep_coffee", "frequency": 0.2975311279296875, "start_frame": 122, "end_frame": 168}, {"scene": 5, "hex_color": "#4c3838", "closest_cm_color_name": "taupe", "frequency": 0.198638916015625, "start_frame": 122, "end_frame": 168}, {"scene": 5, "hex_color": "#1e1917", "closest_cm_color_name": "metropolis", "frequency": 0.1078338623046875, "start_frame": 122, "end_frame": 168}, {"scene": 5, "hex_color": "#bca5cb", "closest_cm_color_name": "silver", "frequency": 0.097747802734375, "start_frame": 122, "end_frame": 168}, {"scene": 6, "hex_color": "#a18aa8", "closest_cm_color_name": "coin", "frequency": 0.31109619140625, "start_frame": 168, "end_frame": 202}, {"scene": 6, "hex_color": "#c0b6dd", "closest_cm_color_name": "cloud", "frequency": 0.2713470458984375, "start_frame": 168, "end_frame": 202}, {"scene": 6, "hex_color": "#81616a", "closest_cm_color_name": "dark_silver", "frequency": 0.219207763671875, "start_frame": 168, "end_frame": 202}, {"scene": 6, "hex_color": "#3f2b26", "closest_cm_color_name": "bistre", "frequency": 0.1509552001953125, "start_frame": 168, "end_frame": 202}, {"scene": 6, "hex_color": "#2b479d", "closest_cm_color_name": "b_dazzled", "frequency": 0.047393798828125, "start_frame": 168, "end_frame": 202}, {"scene": 7, "hex_color": "#c8c2e3", "closest_cm_color_name": "thistle", "frequency": 0.403045654296875, "start_frame": 202, "end_frame": 227}, {"scene": 7, "hex_color": "#125bce", "closest_cm_color_name": "bayern_blue", "frequency": 0.1855316162109375, "start_frame": 202, "end_frame": 227}, {"scene": 7, "hex_color": "#113291", "closest_cm_color_name": "egyptian_blue", "frequency": 0.1451873779296875, "start_frame": 202, "end_frame": 227}, {"scene": 7, "hex_color": "#7a7fb1", "closest_cm_color_name": "flint", "frequency": 0.143218994140625, "start_frame": 202, "end_frame": 227}, {"scene": 7, "hex_color": "#201d35", "closest_cm_color_name": "denim", "frequency": 0.123016357421875, "start_frame": 202, "end_frame": 227}, {"scene": 8, "hex_color": "#1b1221", "closest_cm_color_name": "cool_black", "frequency": 0.315155029296875, "start_frame": 227, "end_frame": 255}, {"scene": 8, "hex_color": "#aea0c0", "closest_cm_color_name": "silver", "frequency": 0.214385986328125, "start_frame": 227, "end_frame": 255}, {"scene": 8, "hex_color": "#90798a", "closest_cm_color_name": "rocket_metallic", "frequency": 0.1857452392578125, "start_frame": 227, "end_frame": 255}, {"scene": 8, "hex_color": "#5f4147", "closest_cm_color_name": "ash", "frequency": 0.1455078125, "start_frame": 227, "end_frame": 255}, {"scene": 8, "hex_color": "#19286b", "closest_cm_color_name": "blueberry", "frequency": 0.1392059326171875, "start_frame": 227, "end_frame": 255}, {"scene": 9, "hex_color": "#93758b", "closest_cm_color_name": "rocket_metallic", "frequency": 0.2808380126953125, "start_frame": 255, "end_frame": 275}, {"scene": 9, "hex_color": "#644c64", "closest_cm_color_name": "fog", "frequency": 0.219207763671875, "start_frame": 255, "end_frame": 275}, {"scene": 9, "hex_color": "#170e28", "closest_cm_color_name": "cool_black", "frequency": 0.1850128173828125, "start_frame": 255, "end_frame": 275}, {"scene": 9, "hex_color": "#13237f", "closest_cm_color_name": "navy", "frequency": 0.1698760986328125, "start_frame": 255, "end_frame": 275}, {"scene": 9, "hex_color": "#b7a8ca", "closest_cm_color_name": "silver", "frequency": 0.1450653076171875, "start_frame": 255, "end_frame": 275}, {"scene": 10, "hex_color": "#2f2123", "closest_cm_color_name": "charcoal", "frequency": 0.2559356689453125, "start_frame": 275, "end_frame": 292}, {"scene": 10, "hex_color": "#a1abe5", "closest_cm_color_name": "silver", "frequency": 0.2525787353515625, "start_frame": 275, "end_frame": 292}, {"scene": 10, "hex_color": "#a08799", "closest_cm_color_name": "vintage_gray", "frequency": 0.1938018798828125, "start_frame": 275, "end_frame": 292}, {"scene": 10, "hex_color": "#74545b", "closest_cm_color_name": "fog", "frequency": 0.159698486328125, "start_frame": 275, "end_frame": 292}, {"scene": 10, "hex_color": "#74150c", "closest_cm_color_name": "berry", "frequency": 0.1379852294921875, "start_frame": 275, "end_frame": 292}, {"scene": 11, "hex_color": "#ebe9f0", "closest_cm_color_name": "shadow_white", "frequency": 0.2503814697265625, "start_frame": 292, "end_frame": 325}, {"scene": 11, "hex_color": "#2e2a3d", "closest_cm_color_name": "gunmetal", "frequency": 0.24798583984375, "start_frame": 292, "end_frame": 325}, {"scene": 11, "hex_color": "#d29898", "closest_cm_color_name": "tumbleweed", "frequency": 0.2392120361328125, "start_frame": 292, "end_frame": 325}, {"scene": 11, "hex_color": "#b34d48", "closest_cm_color_name": "blush_red", "frequency": 0.145843505859375, "start_frame": 292, "end_frame": 325}, {"scene": 11, "hex_color": "#6b647c", "closest_cm_color_name": "pewter", "frequency": 0.1165771484375, "start_frame": 292, "end_frame": 325}, {"scene": 12, "hex_color": "#351d1c", "closest_cm_color_name": "umber", "frequency": 0.2270965576171875, "start_frame": 325, "end_frame": 341}, {"scene": 12, "hex_color": "#7b382e", "closest_cm_color_name": "bole", "frequency": 0.2167205810546875, "start_frame": 325, "end_frame": 341}, {"scene": 12, "hex_color": "#a0838b", "closest_cm_color_name": "stone_gray", "frequency": 0.1963653564453125, "start_frame": 325, "end_frame": 341}, {"scene": 12, "hex_color": "#758ecf", "closest_cm_color_name": "blue_gray", "frequency": 0.19281005859375, "start_frame": 325, "end_frame": 341}, {"scene": 12, "hex_color": "#bcbbea", "closest_cm_color_name": "beau_blue", "frequency": 0.1670074462890625, "start_frame": 325, "end_frame": 341}, {"scene": 13, "hex_color": "#4c96f8", "closest_cm_color_name": "berry_blue", "frequency": 0.418914794921875, "start_frame": 341, "end_frame": 377}, {"scene": 13, "hex_color": "#76a7f3", "closest_cm_color_name": "argentina_blue", "frequency": 0.2609100341796875, "start_frame": 341, "end_frame": 377}, {"scene": 13, "hex_color": "#bdcdf8", "closest_cm_color_name": "beau_blue", "frequency": 0.25164794921875, "start_frame": 341, "end_frame": 377}, {"scene": 13, "hex_color": "#4355a6", "closest_cm_color_name": "b_dazzled", "frequency": 0.039398193359375, "start_frame": 341, "end_frame": 377}, {"scene": 13, "hex_color": "#070d1c", "closest_cm_color_name": "black_magic", "frequency": 0.0291290283203125, "start_frame": 341, "end_frame": 377}, {"scene": 14, "hex_color": "#643f35", "closest_cm_color_name": "deep_coffee", "frequency": 0.25701904296875, "start_frame": 377, "end_frame": 422}, {"scene": 14, "hex_color": "#9d6b49", "closest_cm_color_name": "dirt", "frequency": 0.2337646484375, "start_frame": 377, "end_frame": 422}, {"scene": 14, "hex_color": "#2d1a18", "closest_cm_color_name": "charcoal", "frequency": 0.209503173828125, "start_frame": 377, "end_frame": 422}, {"scene": 14, "hex_color": "#beadca", "closest_cm_color_name": "silver", "frequency": 0.156219482421875, "start_frame": 377, "end_frame": 422}, {"scene": 14, "hex_color": "#d4976a", "closest_cm_color_name": "antique_brass", "frequency": 0.14349365234375, "start_frame": 377, "end_frame": 422}, {"scene": 15, "hex_color": "#2d2c34", "closest_cm_color_name": "iron", "frequency": 0.3059234619140625, "start_frame": 422, "end_frame": 467}, {"scene": 15, "hex_color": "#987473", "closest_cm_color_name": "beaver", "frequency": 0.2154541015625, "start_frame": 422, "end_frame": 467}, {"scene": 15, "hex_color": "#bf97a0", "closest_cm_color_name": "khaki", "frequency": 0.1866607666015625, "start_frame": 422, "end_frame": 467}, {"scene": 15, "hex_color": "#784c46", "closest_cm_color_name": "bole", "frequency": 0.159210205078125, "start_frame": 422, "end_frame": 467}, {"scene": 15, "hex_color": "#e6d3d9", "closest_cm_color_name": "bone", "frequency": 0.13275146484375, "start_frame": 422, "end_frame": 467}, {"scene": 16, "hex_color": "#201528", "closest_cm_color_name": "black_denim", "frequency": 0.2201385498046875, "start_frame": 467, "end_frame": 487}, {"scene": 16, "hex_color": "#636090", "closest_cm_color_name": "ultra_violet", "frequency": 0.218994140625, "start_frame": 467, "end_frame": 487}, {"scene": 16, "hex_color": "#9e6c63", "closest_cm_color_name": "chamoisee", "frequency": 0.21044921875, "start_frame": 467, "end_frame": 487}, {"scene": 16, "hex_color": "#122681", "closest_cm_color_name": "navy", "frequency": 0.1867523193359375, "start_frame": 467, "end_frame": 487}, {"scene": 16, "hex_color": "#afa7cb", "closest_cm_color_name": "silver", "frequency": 0.163665771484375, "start_frame": 467, "end_frame": 487}, {"scene": 17, "hex_color": "#2a2023", "closest_cm_color_name": "raisin_black", "frequency": 0.2287750244140625, "start_frame": 487, "end_frame": 514}, {"scene": 17, "hex_color": "#658dd3", "closest_cm_color_name": "blue_gray", "frequency": 0.2072906494140625, "start_frame": 487, "end_frame": 514}, {"scene": 17, "hex_color": "#9c797c", "closest_cm_color_name": "beaver", "frequency": 0.20196533203125, "start_frame": 487, "end_frame": 514}, {"scene": 17, "hex_color": "#75271f", "closest_cm_color_name": "brick", "frequency": 0.1963958740234375, "start_frame": 487, "end_frame": 514}, {"scene": 17, "hex_color": "#afb7e9", "closest_cm_color_name": "beau_blue", "frequency": 0.1655731201171875, "start_frame": 487, "end_frame": 514}, {"scene": 18, "hex_color": "#eddff3", "closest_cm_color_name": "aircraft_white", "frequency": 0.3890228271484375, "start_frame": 514, "end_frame": 557}, {"scene": 18, "hex_color": "#855758", "closest_cm_color_name": "coconut", "frequency": 0.283721923828125, "start_frame": 514, "end_frame": 557}, {"scene": 18, "hex_color": "#a2757c", "closest_cm_color_name": "beaver", "frequency": 0.136322021484375, "start_frame": 514, "end_frame": 557}, {"scene": 18, "hex_color": "#bfa5bb", "closest_cm_color_name": "gray_cloud", "frequency": 0.10125732421875, "start_frame": 514, "end_frame": 557}, {"scene": 18, "hex_color": "#3c2b39", "closest_cm_color_name": "iron", "frequency": 0.0896759033203125, "start_frame": 514, "end_frame": 557}, {"scene": 19, "hex_color": "#976c57", "closest_cm_color_name": "dirt", "frequency": 0.2883453369140625, "start_frame": 557, "end_frame": 599}, {"scene": 19, "hex_color": "#6a4730", "closest_cm_color_name": "coffee", "frequency": 0.234893798828125, "start_frame": 557, "end_frame": 599}, {"scene": 19, "hex_color": "#222225", "closest_cm_color_name": "raisin_black", "frequency": 0.2176666259765625, "start_frame": 557, "end_frame": 599}, {"scene": 19, "hex_color": "#9e90a8", "closest_cm_color_name": "coin", "frequency": 0.1695098876953125, "start_frame": 557, "end_frame": 599}, {"scene": 19, "hex_color": "#cec3dc", "closest_cm_color_name": "thistle", "frequency": 0.0895843505859375, "start_frame": 557, "end_frame": 599}, {"scene": 20, "hex_color": "#2b2237", "closest_cm_color_name": "dark_purple", "frequency": 0.3218841552734375, "start_frame": 599, "end_frame": 642}, {"scene": 20, "hex_color": "#ccd9f8", "closest_cm_color_name": "beau_blue", "frequency": 0.311004638671875, "start_frame": 599, "end_frame": 642}, {"scene": 20, "hex_color": "#5d4d5c", "closest_cm_color_name": "graphite", "frequency": 0.1931304931640625, "start_frame": 599, "end_frame": 642}, {"scene": 20, "hex_color": "#a37470", "closest_cm_color_name": "beaver", "frequency": 0.104583740234375, "start_frame": 599, "end_frame": 642}, {"scene": 20, "hex_color": "#938fb2", "closest_cm_color_name": "coin", "frequency": 0.06939697265625, "start_frame": 599, "end_frame": 642}, {"scene": 21, "hex_color": "#90a5d8", "closest_cm_color_name": "ruddy_blue", "frequency": 0.5549468994140625, "start_frame": 642, "end_frame": 752}, {"scene": 21, "hex_color": "#52533b", "closest_cm_color_name": "gray_wolf", "frequency": 0.1765899658203125, "start_frame": 642, "end_frame": 752}, {"scene": 21, "hex_color": "#181526", "closest_cm_color_name": "cool_black", "frequency": 0.1397247314453125, "start_frame": 642, "end_frame": 752}, {"scene": 21, "hex_color": "#767a98", "closest_cm_color_name": "flint", "frequency": 0.0773162841796875, "start_frame": 642, "end_frame": 752}, {"scene": 21, "hex_color": "#255db6", "closest_cm_color_name": "blue", "frequency": 0.051422119140625, "start_frame": 642, "end_frame": 752}]}}